velocitas/__init__.py
velocitas/model_generator/__init__.py
velocitas/model_generator/cli.py
velocitas/model_generator/utils.py
velocitas/model_generator/cpp/__init__.py
velocitas/model_generator/cpp/cpp_generator.py
velocitas/model_generator/cpp/cpp_keywords.py
velocitas/model_generator/python/__init__.py
velocitas/model_generator/python/python_generator.py
velocitas/model_generator/python/vss_collection.py
velocitas/model_generator/tree_generator/__init__.py
velocitas/model_generator/tree_generator/constants.py
velocitas/model_generator/tree_generator/file_formats.py
velocitas/model_generator/tree_generator/file_import.py
velocitas_model_generator-0.8.0.dist-info/licenses/LICENSE
velocitas_model_generator-0.8.0.dist-info/licenses/NOTICE-3RD-PARTY-CONTENT.md
velocitas_model_generator-0.8.0.dist-info/licenses/NOTICE.md
velocitas_model_generator-0.8.0.dist-info/METADATA
velocitas_model_generator-0.8.0.dist-info/WHEEL
velocitas_model_generator-0.8.0.dist-info/entry_points.txt
velocitas_model_generator-0.8.0.dist-info/top_level.txt
velocitas_model_generator-0.8.0.dist-info/RECORD
