Metadata-Version: 2.4
Name: velocitas_model_generator
Version: 0.8.0
Summary: Generates a language-specific data model out of VSS vspec files
License:                                  Apache License
Requires-Python: >=3.10
License-File: LICENSE
License-File: NOTICE-3RD-PARTY-CONTENT.md
License-File: NOTICE.md
Requires-Dist: vss-tools==4.0
Dynamic: license-file
